[
  [
    { "label": "Rope Dynamic Elongation", "value": "0.34" },
    { "label": "Rope Factor Falls", "value": "7" },
    { "label": "Rope Half Mark", "value": "Yes" },
    { "label": "Rope Impact Force", "value": "8 kN" },
    { "label": "Rope Sheath Slippage", "value": "-0.001" },
    { "label": "Rope Static Elongation", "value": "0.084" },
    { "label": "Rope Type", "value": "Single" },
    { "label": "Rope Weight Per Meter", "value": "58 g (2.05 oz)" }
  ],
  [
    { "label": "Rope Dynamic Elongation", "value": "37%" },
    { "label": "Rope Factor Falls", "value": "6" },
    { "label": "Rope Half Mark", "value": "Yes" },
    { "label": "Rope Impact Force", "value": "7.9 kN" },
    { "label": "Rope Sheath Slippage", "value": "0%" },
    { "label": "Rope Static Elongation", "value": "6.4%" },
    { "label": "Rope Type", "value": "Single" },
    { "label": "Rope Weight Per Meter", "value": "58 g (2.05 oz)" }
  ],
  [
    { "label": "Rope Dynamic Elongation", "value": "0.26" },
    { "label": "Rope Factor Falls", "value": "7" },
    { "label": "Rope Half Mark", "value": "Yes" },
    { "label": "Rope Impact Force", "value": "9.4 kN" },
    { "label": "Rope Static Elongation", "value": "0.033" },
    { "label": "Rope Type", "value": "Single" },
    { "label": "Rope Weight Per Meter", "value": "60 g (2.3 oz)" },
    { "label": "Rope Sheath Slippage", "value": "+/- .01" }
  ],
  [
    { "label": "Rope Factor Falls", "value": "9" },
    { "label": "Rope Half Mark", "value": "Yes" },
    { "label": "Rope Type", "value": "Single" },
    { "label": "Rope Weight Per Meter", "value": "58 g/m" },
    { "label": "Size Range", "value": "60m, 70m, 80m" }
  ],
  [
    { "label": "Rope Factor Falls", "value": "6" },
    { "label": "Rope Half Mark", "value": "Yes" },
    { "label": "Rope Type", "value": "Single" },
    { "label": "Rope Weight Per Meter", "value": "58 g/m" }
  ],
  [
    { "label": "Rope Dynamic Elongation", "value": "35% [Half] 33% [Twin]" },
    { "label": "Rope Factor Falls", "value": "10 [Half] 17 [Twin]" },
    { "label": "Rope Half Mark", "value": "Yes" },
    { "label": "Rope Impact Force", "value": "5 kN [Half] 7.7 [Twin]" },
    { "label": "Rope Sheath Slippage", "value": "0.001" },
    { "label": "Rope Static Elongation", "value": "7% [Half and Twin]" },
    { "label": "Rope Type", "value": "Half/Twin" },
    { "label": "Rope Weight Per Meter", "value": "46 g (1.62 oz)" }
  ],
  [
    { "label": "Rope Factor Falls", "value": "7" },
    { "label": "Rope Half Mark", "value": "Yes" },
    { "label": "Rope Type", "value": "Single" },
    { "label": "Rope Weight Per Meter", "value": "61 g/m" },
    { "label": "Size Range", "value": "60m, 70m, 80m" }
  ],
  [
    { "label": "Rope Dynamic Elongation", "value": "0.33" },
    { "label": "Rope Factor Falls", "value": "5" },
    { "label": "Rope Half Mark", "value": "Yes" },
    { "label": "Rope Impact Force", "value": "8.2 kN" },
    { "label": "Rope Static Elongation", "value": "0.054" },
    { "label": "Rope Type", "value": "Single" },
    { "label": "Rope Weight Per Meter", "value": "66 g/m" }
  ],
  [
    { "label": "Rope Factor Falls", "value": "9" },
    { "label": "Rope Half Mark", "value": "Yes" },
    { "label": "Rope Type", "value": "Single" },
    { "label": "Rope Weight Per Meter", "value": "58 g/m" },
    { "label": "Size Range", "value": "60m, 70m, 80m" }
  ],
  [
    { "label": "Rope Dynamic Elongation", "value": "33%/30%/27%" },
    { "label": "Rope Factor Falls", "value": "05/16/29" },
    { "label": "Rope Half Mark", "value": "Yes" },
    { "label": "Rope Impact Force", "value": "8.7 kN/6.1 kN/9.6 kN" },
    { "label": "Rope Static Elongation", "value": "0.069" },
    { "label": "Rope Type", "value": "Single/Half/Twin" },
    { "label": "Rope Weight Per Meter", "value": "52" }
  ],
  [
    { "label": "Rope Factor Falls", "value": "7" },
    { "label": "Rope Half Mark", "value": "Yes" },
    { "label": "Rope Type", "value": "Single" },
    { "label": "Rope Weight Per Meter", "value": "61 g/m" },
    { "label": "Size Range", "value": "60m, 70m, 80m" }
  ],
  [
    { "label": "Rope Dynamic Elongation", "value": "33% [Twin Rope]" },
    { "label": "Rope Factor Falls", "value": "14 [Twin Rope]" },
    { "label": "Rope Half Mark", "value": "Yes" },
    { "label": "Rope Impact Force", "value": "8.9 kN [Twin Rope]" },
    { "label": "Rope Static Elongation", "value": "3.6% [Twin Rope]" },
    { "label": "Rope Type", "value": "Twin Rope" },
    { "label": "Rope Weight Per Meter", "value": "34 g (1.2 oz)" }
  ],
  [
    { "label": "Rope Dynamic Elongation", "value": "34% [Half] 32% [Twin]" },
    { "label": "Rope Factor Falls", "value": "6 [Half] 16 [Twin]" },
    { "label": "Rope Half Mark", "value": "Yes" },
    { "label": "Rope Impact Force", "value": "5.4 kN [Half] 7.8 kN [Twin]" },
    { "label": "Rope Static Elongation", "value": "6.7% [Half] 7% [Twin]" },
    { "label": "Rope Type", "value": "Half/Twin" },
    { "label": "Rope Weight Per Meter", "value": "39 g  (1.38 oz)" }
  ],
  [
    { "label": "Rope Type", "value": "Static Kernmantel Accessory Cord" },
    { "label": "Rope Weight Per Meter", "value": "27.4 g/m" }
  ],
  [
    { "label": "Length", "value": "65m" },
    { "label": "Rope Type", "value": "Static" },
    { "label": "Rope Weight Per Meter", "value": "50 g/m" }
  ],
  [
    { "label": "Rope Half Mark", "value": "No" },
    { "label": "Rope Sheath Slippage", "value": "4 mm" },
    { "label": "Rope Static Elongation", "value": "0.034" },
    { "label": "Rope Type", "value": "Static Type A Low Stretch Kernmantel Rope" },
    { "label": "Rope Weight Per Meter", "value": "69 g/m" }
  ],
  [{ "label": "Rope Weight Per Meter", "value": "66 g/m" }],
  [{ "label": "Rope Weight Per Meter", "value": "69 g/m" }],
  []
]
